qwind/__init__.py
qwind/constants.py
qwind/integration.py
qwind/plotting.py
qwind/streamline.py
qwind/utils.py
qwind/wind.py
qwind/radiation/__init__.py
qwind/radiation/simple_sed.py
test/__init__.py
test/test_integration.py
test/test_simplesed.py
test/test_streamline_class.py
test/test_wind_class.py
Qwind-0.0.1.dev89.dist-info/AUTHORS
Qwind-0.0.1.dev89.dist-info/LICENSE
Qwind-0.0.1.dev89.dist-info/METADATA
Qwind-0.0.1.dev89.dist-info/WHEEL
Qwind-0.0.1.dev89.dist-info/pbr.json
Qwind-0.0.1.dev89.dist-info/top_level.txt
Qwind-0.0.1.dev89.dist-info/RECORD
