Metadata-Version: 2.1
Name: Qwind
Version: 0.0.1.dev89
Summary: AGN line-driven winds model.
Home-page: https://github.com/arnauqb/qwind
Author: Arnau Quera-Bofarull
Author-email: arnau.quera-bofarull@durham.ac.uk
License: GPL
Platform: UNKNOWN
Requires-Python: >=3.6
Requires-Dist: astropy (==3.2.1)
Requires-Dist: llvmlite (==0.29.0)
Requires-Dist: numba (==0.45.0)
Requires-Dist: numpy (==1.16.4)
Requires-Dist: scipy (==1.3.0)
Requires-Dist: tqdm (==4.32.1)
Requires-Dist: pytest (==5.0.1)
Requires-Dist: pytest-cov (==2.7.1)
Requires-Dist: codecov (==2.0.15)
Requires-Dist: pandas (==0.24.2)
Requires-Dist: qsosed (==0.0.1.dev52)
